authena_python_sdk/__init__.py
authena_python_sdk/client.py
authena_python_sdk/client_base.py
authena_python_sdk/client_group.py
authena_python_sdk/client_user.py
authena_python_sdk/config.py
authena_python_sdk/models/__init__.py
authena_python_sdk/models/group.py
authena_python_sdk/models/token.py
authena_python_sdk/models/user.py
authena_python_sdk_tests/integration/__init__.py
authena_python_sdk_tests/integration/conftest.py
authena_python_sdk_tests/integration/fixtures/__init__.py
authena_python_sdk_tests/integration/fixtures/group.py
authena_python_sdk_tests/integration/fixtures/sdk_client.py
authena_python_sdk_tests/integration/fixtures/user.py
authena_python_sdk_tests/integration/tests/__init__.py
authena_python_sdk_tests/integration/tests/group/__init__.py
authena_python_sdk_tests/integration/tests/group/test_create.py
authena_python_sdk_tests/integration/tests/group/test_delete.py
authena_python_sdk_tests/integration/tests/group/test_filter.py
authena_python_sdk_tests/integration/tests/group/test_get.py
authena_python_sdk_tests/integration/tests/group/test_update.py
authena_python_sdk_tests/integration/tests/permission/__init__.py
authena_python_sdk_tests/integration/tests/permission/test_get.py
authena_python_sdk_tests/integration/tests/token/__init__.py
authena_python_sdk_tests/integration/tests/token/test_challenge.py
authena_python_sdk_tests/integration/tests/token/test_create.py
authena_python_sdk_tests/integration/tests/token/test_refresh.py
authena_python_sdk_tests/integration/tests/token/test_validate.py
authena_python_sdk_tests/integration/tests/user/__init__.py
authena_python_sdk_tests/integration/tests/user/test_create.py
authena_python_sdk_tests/integration/tests/user/test_delete.py
authena_python_sdk_tests/integration/tests/user/test_disable.py
authena_python_sdk_tests/integration/tests/user/test_enable.py
authena_python_sdk_tests/integration/tests/user/test_filter.py
authena_python_sdk_tests/integration/tests/user/test_get.py
authena_python_sdk-0.0.5.dist-info/LICENSE
authena_python_sdk-0.0.5.dist-info/METADATA
authena_python_sdk-0.0.5.dist-info/WHEEL
authena_python_sdk-0.0.5.dist-info/top_level.txt
authena_python_sdk-0.0.5.dist-info/RECORD
