Metadata-Version: 2.1
Name: authena-python-sdk
Version: 0.0.5
Summary: Authena Python SDK
Home-page: https://github.com/Biomapas/AuthenaPythonSDK.git
Author: Gediminas Kazlauskas
Author-email: gediminas.kazlauskas@biomapas.com
License: Apache License 2.0
Keywords: Authena Python SDK
Platform: UNKNOWN
Classifier: Programming Language :: Python :: 3
Classifier: Operating System :: OS Independent
Requires-Dist: b-lambda-layer-common (<4.0.0,>=3.0.1)
